{
  "_note1": "KEEP THIS FILE! Check it into a version control system (VCS) like git.",
  "_note2": "ObjectBox manages crucial IDs for your object model. See docs for details.",
  "_note3": "If you have VCS merge conflicts, you must resolve them according to ObjectBox docs.",
  "entities": [
    {
      "id": "1:9010798967777340560",
      "lastPropertyId": "8:5867635433896042515",
      "name": "Song",
      "properties": [
        {
          "id": "1:7159351169199739191",
          "name": "id",
          "type": 6,
          "flags": 1
        },
        {
          "id": "2:3115723590380257770",
          "name": "name",
          "type": 9
        },
        {
          "id": "3:8594253787416493472",
          "name": "artist",
          "type": 9
        },
        {
          "id": "4:614895528964824454",
          "name": "spotifyId",
          "type": 9,
          "flags": 2080,
          "indexId": "1:3324877264777455464"
        },
        {
          "id": "6:2913082945644414994",
          "name": "dateAdded",
          "type": 10
        },
        {
          "id": "7:4633956051513000642",
          "name": "releaseDate",
          "type": 10
        },
        {
          "id": "8:5867635433896042515",
          "name": "duration",
          "type": 6
        }
      ],
      "relations": [
        {
          "id": "1:2933435051223473136",
          "name": "tags",
          "targetId": "2:3379074201238304732"
        }
      ]
    },
    {
      "id": "2:3379074201238304732",
      "lastPropertyId": "5:8200168161526390469",
      "name": "Tag",
      "properties": [
        {
          "id": "2:190164107148731585",
          "name": "id",
          "type": 6,
          "flags": 1
        },
        {
          "id": "3:4695901502359810162",
          "name": "name",
          "type": 9
        },
        {
          "id": "4:1302384689009912107",
          "name": "colourIndex",
          "type": 6
        },
        {
          "id": "5:8200168161526390469",
          "name": "userDefined",
          "type": 1
        }
      ],
      "relations": []
    },
    {
      "id": "7:2557409868432952656",
      "lastPropertyId": "5:8766596034594712122",
      "name": "PlaybackFilter",
      "properties": [
        {
          "id": "1:7586258636854530005",
          "name": "id",
          "type": 6,
          "flags": 1
        },
        {
          "id": "2:2872838993623638644",
          "name": "name",
          "type": 9
        },
        {
          "id": "3:8369491077183155537",
          "name": "lastAccessed",
          "type": 10
        },
        {
          "id": "4:8187612926945003173",
          "name": "dbTotalByVersion",
          "type": 9
        }
      ],
      "relations": [
        {
          "id": "2:6374847314963343384",
          "name": "tags",
          "targetId": "2:3379074201238304732"
        }
      ]
    }
  ],
  "lastEntityId": "7:2557409868432952656",
  "lastIndexId": "1:3324877264777455464",
  "lastRelationId": "2:6374847314963343384",
  "lastSequenceId": "0:0",
  "modelVersion": 5,
  "modelVersionParserMinimum": 5,
  "retiredEntityUids": [
    8001341518230850695,
    2695809420363043732,
    6305852949951424807,
    7901599631224104933
  ],
  "retiredIndexUids": [],
  "retiredPropertyUids": [
    5489380764927646302,
    347302859567081836,
    6995005639536957438,
    6977115435854106704,
    8652738848562534240,
    2553839442597324993,
    3719602983658599573,
    3692236497740312392,
    1605686068252087171,
    8930213380727279550,
    6309408186515916460,
    7831192010280214150,
    6060519888185551742,
    1692085368193444789,
    6629946317230573522,
    983891003222283668,
    7727123918288359283,
    2015158093280157473,
    7126892046675706469,
    2700315743673163372,
    6152311172718504653,
    8766596034594712122
  ],
  "retiredRelationUids": [],
  "version": 1
}